{"slug": "examples/charts", "html": {"main": "<h2 id=\"simple-chart\">Simple Chart</h2>\n<div data-options='examples.sigmoid' style='max-width: 500px' data-height='80%' data-viz-chart></div>"}, "site": {"url": "http://quantmind.github.io/giotto", "date": "2014-11-21T11-36-43", "name": "Lux", "python_version": "3.4.2", "media": "/media", "year": 2014, "lux_version": "0.1.1-alpha.1", "template": null, "template_engine": null}, "html_url": "http://quantmind.github.io/giotto/examples/charts", "head": {}, "modified": "2014-11-13T07:43:07", "name": "examples_charts", "api_url": "http://quantmind.github.io/giotto/ng/site/examples/charts.json", "content_type": "text/html"}