{"api_url": "http://giottojs.org/ng/site/download.json", "title": "GiottoJS - Download", "modified": "2014-12-10T13:58:47", "image": "http://giottojs.org/media/giottoweb/giotto.png", "name": "download", "html_url": "http://giottojs.org/download", "html": {"main": "<div id=\"page-main\">\n<div class=\"container\">\n<div class=\"row\">\n<div class=\"col-sm-12\">\n<div class=\"page-header\">\n<h2>GiottoJS - Download</h2>\n</div>\n<div data-highlight>\n<p>Latest development versions</p>\n<ul>\n<li><a href=\"http://quantmind.github.io/giotto/media/giotto/giotto.js\">giotto.js</a></li>\n<li><a href=\"http://quantmind.github.io/giotto/media/giotto/giotto.min.js\">giotto.min.js</a></li>\n</ul>\n<p><a href=\"https://travis-ci.org/quantmind/giotto\" target=\"_self\">\n<img src=\"https://travis-ci.org/quantmind/giotto.svg?branch=master\" alt=\"giotto CI\"></a>\n<a href=\"https://coveralls.io/r/quantmind/giotto?branch=master\"><img alt=\"Coverage Status\" src=\"https://img.shields.io/coveralls/quantmind/giotto.svg\" /></a></p>\n</div>\n</div>\n</div>\n</div>\n</div>\n<div id=\"footer\">\n<div class=\"container\">\n<div class=\"row\">\n<div class=\"col-sm-12 small\">\n<p>Library released under the <a href=\"http://opensource.org/licenses/BSD-3-Clause\">BSD License</a>.</p>\n<p>Copyright 2014 <a href=\"http://lucasbardella.com\">Luca Sbardella</a> and <a href=\"http://quantmind.com\">Quantmind</a></p>\n</div>\n</div>\n</div>\n</div>"}, "content_type": "text/html", "head": {"title": "GiottoJS - Download", "twitter:card": "summary_large_image"}, "slug": "download", "site": {"date": "2014-12-31T08-54-04", "media": "/media", "url": "http://giottojs.org", "template": "partials/base.html", "name": "Lux", "year": 2014, "lux_version": "0.1.2-alpha.1", "template_engine": null, "python_version": "3.4.2"}}