{"modified": "2014-12-17T10:42:01", "html": {"main": "<div class=\"page-header\">\n<h2>Giotto Examples</h2>\n</div>\n<div data-blog-pagination></div>"}, "html_url": "http://giottojs.org/examples/", "name": "index", "slug": "index", "head": {"twitter:card": "summary_large_image"}, "content_type": "text/html", "api_url": "http://giottojs.org/ng/examples/index.json", "site": {"date": "2014-12-17T15-24-02", "lux_version": "0.1.2-alpha.1", "template_engine": null, "name": "Lux", "media": "/media", "year": 2014, "url": "http://giottojs.org", "template": null, "python_version": "3.4.2"}}