[{"author": ["Luca Sbardella"], "title": "Zooming", "content_type": "text/html", "date": "2014-12-18T00:00:00", "name": "zooming", "image": "http://giottojs.org/examples/zooming.png", "html_url": "http://giottojs.org/examples/zooming", "description": "Zooming on SVG and Canvas with GiottoJS using d3js behavour zoom", "slug": "zooming", "api_url": "http://giottojs.org/ng/examples/zooming.json", "modified": "2014-12-18T17:55:56"}, {"author": ["Luca Sbardella"], "title": "Simple Bar Chart", "content_type": "text/html", "date": "2014-12-18T00:00:00", "name": "barchart", "image": "http://giottojs.org/examples/barchart.png", "html_url": "http://giottojs.org/examples/barchart", "description": "A simple bar chart on canvas or svg", "slug": "barchart", "api_url": "http://giottojs.org/ng/examples/barchart.json", "modified": "2014-12-18T14:28:29"}, {"author": ["Luca Sbardella"], "title": "GiottoJS Logo", "content_type": "text/html", "date": "2014-12-17T00:00:00", "name": "giottologo", "image": "http://giottojs.org/examples/giottologo.png", "html_url": "http://giottojs.org/examples/giottologo", "description": "GiottoJS logo created using nested pie charts. It uses the latest d3js pie layout features such as pad angles and curved corners. Both SVG and Canvas supported.", "slug": "giottologo", "api_url": "http://giottojs.org/ng/examples/giottologo.json", "modified": "2014-12-18T13:15:16"}, {"author": ["Luca Sbardella"], "title": "2011 World Wine Production", "content_type": "text/html", "date": "2014-12-14T00:00:00", "name": "wineproduction", "image": "http://giottojs.org/examples/wineproduction.png", "html_url": "http://giottojs.org/examples/wineproduction", "description": "Illustrate several options when visualizing data with a pie chart using GiottoJS. Both canvas and svg are supported.", "slug": "wineproduction", "api_url": "http://giottojs.org/ng/examples/wineproduction.json", "modified": "2014-12-18T13:16:11"}, {"author": ["Luca Sbardella"], "title": "Lines and Symbols", "content_type": "text/html", "date": "2014-12-14T00:00:00", "name": "linetypes", "image": "http://giottojs.org/examples/linetypes.png", "html_url": "http://giottojs.org/examples/linetypes", "description": "A run-through of all the options available when plotting lines and points on a chart. It shows how to use d3js line and symbol for both SVG and CANVAS.", "slug": "linetypes", "api_url": "http://giottojs.org/ng/examples/linetypes.json", "modified": "2014-12-18T13:15:10"}, {"author": ["Luca Sbardella"], "title": "Trianglify", "content_type": "text/html", "date": "2014-12-04T00:00:00", "name": "trianglify", "image": "http://giottojs.org/examples/trianglify.svg", "html_url": "http://giottojs.org/examples/trianglify", "description": "Use the Trianglify Javascript library to create background images with Delaunay triangulation", "slug": "trianglify", "api_url": "http://giottojs.org/ng/examples/trianglify.json", "modified": "2014-12-18T13:15:31"}, {"author": ["Luca Sbardella"], "title": "Simple Chart", "content_type": "text/html", "date": "2014-12-03T00:00:00", "name": "simplechart", "image": "http://giottojs.org/examples/simplechart.png", "html_url": "http://giottojs.org/examples/simplechart", "description": "A simple line and point plot of two separate series", "slug": "simplechart", "api_url": "http://giottojs.org/ng/examples/simplechart.json", "modified": "2014-12-18T13:14:43"}, {"name": "brush", "title": "Brushes", "content_type": "text/html", "date": "2014-12-01T00:00:00", "html_url": "http://giottojs.org/examples/brush", "description": "A list of GiottoJS examples", "slug": "brush", "api_url": "http://giottojs.org/ng/examples/brush.json", "modified": "2014-12-01T19:05:05"}, {"name": "bitcoin", "api_url": "http://giottojs.org/ng/examples/bitcoin.json", "title": "Bitcoin timeseries", "content_type": "text/html", "modified": "2014-11-28T21:34:46", "html_url": "http://giottojs.org/examples/bitcoin", "slug": "bitcoin", "description": "A list of GiottoJS examples"}, {"name": "leaflet", "api_url": "http://giottojs.org/ng/examples/leaflet.json", "title": "Leaflet example", "content_type": "text/html", "modified": "2014-11-28T21:34:04", "html_url": "http://giottojs.org/examples/leaflet", "slug": "leaflet", "description": "A list of GiottoJS examples"}, {"name": "collisions", "title": "Collision Detection", "content_type": "text/html", "date": "2014-11-28T00:00:00", "image": "http://giottojs.org/examples/collisions/collision.svg", "html_url": "http://giottojs.org/examples/collisions", "description": "A list of GiottoJS examples", "slug": "collisions", "api_url": "http://giottojs.org/ng/examples/collisions.json", "modified": "2014-12-08T08:41:10"}, {"author": ["Luca Sbardella"], "title": "Zoomable Sunburst Partition", "content_type": "text/html", "date": "2014-11-04T00:00:00", "name": "sunburst", "image": "http://giottojs.org/examples/sunburst.png", "html_url": "http://giottojs.org/examples/sunburst", "description": "Zoomable Sunburst Partition with labels and resizing. Only SVG supported for now", "slug": "sunburst", "api_url": "http://giottojs.org/ng/examples/sunburst.json", "modified": "2014-12-19T10:50:02"}]